{"frames": {

"pumpkin-0.png":
{
	"frame": {"x":0,"y":0,"w":100,"h":100},
	"rotated": false,
	"trimmed": false,
	"spriteSourceSize": {"x":0,"y":0,"w":100,"h":100},
	"sourceSize": {"w":100,"h":100}
},
"pumpkin-1.png":
{
	"frame": {"x":100,"y":0,"w":100,"h":100},
	"rotated": false,
	"trimmed": false,
	"spriteSourceSize": {"x":0,"y":0,"w":100,"h":100},
	"sourceSize": {"w":100,"h":100}
},
"pumpkin-2.png":
{
	"frame": {"x":200,"y":0,"w":100,"h":100},
	"rotated": false,
	"trimmed": false,
	"spriteSourceSize": {"x":0,"y":0,"w":100,"h":100},
	"sourceSize": {"w":100,"h":100}
},
"pumpkin-3.png":
{
	"frame": {"x":300,"y":0,"w":100,"h":100},
	"rotated": false,
	"trimmed": false,
	"spriteSourceSize": {"x":0,"y":0,"w":100,"h":100},
	"sourceSize": {"w":100,"h":100}
}},
"meta": {
	"app": "https://www.codeandweb.com/texturepacker",
	"version": "1.0",
	"image": "pumpkin.png",
	"format": "RGBA8888",
	"size": {"w":400,"h":100},
	"scale": "1",
	"smartupdate": "$TexturePacker:SmartUpdate:5d3933b439811786b200b9910b704aae:9d482a47a739a4ab4465cf13df3cb7fe:62d866bed8d5b8c450b94e43942ad082$"
}
}
